subwer/__init__.py
subwer/core.py
subwer/normalizer.py
subwer/subtitle_reader.py
subwer-0.1.0.dist-info/licenses/LICENSE
tests/__init__.py
tests/test_subwer.py
subwer-0.1.0.dist-info/METADATA
subwer-0.1.0.dist-info/WHEEL
subwer-0.1.0.dist-info/top_level.txt
subwer-0.1.0.dist-info/RECORD
