Metadata-Version: 2.4
Name: subwer
Version: 0.1.0
Summary: A package for calculating Word Error Rate (WER) and Character Error Rate (CER) between subtitle files
Home-page: https://github.com/jhj0517/subwer
Author: jhj0517
Author-email: developerjo0517@gmail.com
License: MIT
Keywords: audio,subtitle,wer,cer,jiwer
Classifier: Development Status :: 3 - Alpha
Classifier: Intended Audience :: Developers
Classifier: Intended Audience :: Science/Research
Classifier: License :: OSI Approved :: MIT License
Classifier: Programming Language :: Python :: 3
Classifier: Programming Language :: Python :: 3.7
Classifier: Programming Language :: Python :: 3.8
Classifier: Programming Language :: Python :: 3.9
Classifier: Programming Language :: Python :: 3.10
Classifier: Programming Language :: Python :: 3.11
Classifier: Programming Language :: Python :: 3.12
Requires-Python: >=3.6
License-File: LICENSE
Requires-Dist: jiwer
Provides-Extra: dev
Requires-Dist: pytest>=7.0.0; extra == "dev"
Dynamic: license-file
